plantsimpath/__init__.py
plantsimpath/path.py
plantsimpath/py.typed
plantsimpath-0.0.4.dist-info/licenses/LICENSE
plantsimpath-0.0.4.dist-info/METADATA
plantsimpath-0.0.4.dist-info/WHEEL
plantsimpath-0.0.4.dist-info/top_level.txt
plantsimpath-0.0.4.dist-info/RECORD
