Metadata-Version: 2.4
Name: plantsimpath
Version: 0.0.4
Summary: A Python helper class to make Plantsim Path usage accessible.
Author-email: Luca Bernstiel <bernstiel@gmx.de>
License-Expression: MIT
Project-URL: Homepage, https://github.com/malun22/plantsim-path
Project-URL: Documentation, https://malun22.github.io/plantsimpath/
Project-URL: Repository, https://github.com/malun22/plantsim-path
Keywords: plant,siemens,simulation,path
Requires-Python: >=3.13
License-File: LICENSE
Dynamic: license-file
